gpytoolbox_bindings_copyleft.cpython-311-darwin.so
gpytoolbox_bindings.cpython-311-darwin.so
libwgpu_native.dylib
gpytoolbox-0.3.7.dist-info/RECORD
gpytoolbox-0.3.7.dist-info/WHEEL
gpytoolbox-0.3.7.dist-info/top_level.txt
gpytoolbox-0.3.7.dist-info/METADATA
gpytoolbox-0.3.7.dist-info/licenses/LICENSE.MIT
gpytoolbox-0.3.7.dist-info/licenses/LICENSE.GPL
gpytoolbox/reach_for_the_spheres.py
gpytoolbox/grid_neighbors.py
gpytoolbox/squared_distance_to_element.py
gpytoolbox/dec_h2_intrinsic.py
gpytoolbox/quadtree_boundary.py
gpytoolbox/colormap.py
gpytoolbox/boundary_edges.py
gpytoolbox/metropolis_hastings.py
gpytoolbox/random_points_on_mesh.py
gpytoolbox/dec_h0inv.py
gpytoolbox/dec_h2inv.py
gpytoolbox/catmull_rom_spline.py
gpytoolbox/point_cloud_to_mesh.py
gpytoolbox/decimate.py
gpytoolbox/gaussian_process.py
gpytoolbox/normalize_points.py
gpytoolbox/doublearea.py
gpytoolbox/biharmonic_energy.py
gpytoolbox/read_dmat.py
gpytoolbox/remesh_botsch.py
gpytoolbox/tip_angles_intrinsic.py
gpytoolbox/halfedge_lengths.py
gpytoolbox/barycenters.py
gpytoolbox/doublearea_intrinsic.py
gpytoolbox/dec_h1inv_intrinsic.py
gpytoolbox/edge_indices.py
gpytoolbox/massmatrix_intrinsic.py
gpytoolbox/read_mesh.py
gpytoolbox/triangle_triangle_adjacency.py
gpytoolbox/signed_distance_polygon.py
gpytoolbox/linear_elasticity.py
gpytoolbox/boundary_vertices.py
gpytoolbox/quadtree_children.py
gpytoolbox/approximate_hausdorff_distance.py
gpytoolbox/halfedge_edge_map.py
gpytoolbox/subdivide.py
gpytoolbox/faces.py
gpytoolbox/cut_edges.py
gpytoolbox/torus.py
gpytoolbox/per_face_normals.py
gpytoolbox/write_mesh.py
gpytoolbox/in_quadtree.py
gpytoolbox/halfedge_lengths_squared.py
gpytoolbox/squared_distance.py
gpytoolbox/angle_defect_intrinsic.py
gpytoolbox/connected_components.py
gpytoolbox/dec_d0.py
gpytoolbox/dec_h0inv_intrinsic.py
gpytoolbox/compactly_supported_normal.py
gpytoolbox/non_manifold_edges.py
gpytoolbox/minimum_distance.py
gpytoolbox/boundary_faces.py
gpytoolbox/in_element_aabb.py
gpytoolbox/massmatrix.py
gpytoolbox/remove_unreferenced.py
gpytoolbox/dec_h1inv.py
gpytoolbox/offset_surface.py
gpytoolbox/quadtree_gradient.py
gpytoolbox/min_quad_with_fixed.py
