Metadata-Version: 2.4
Name: gpytoolbox
Version: 0.3.7
Summary: Gpytoolbox: A Python Geometry Processing Toolbox.
Home-page: https://gpytoolbox.org
Author: Silvia Sellán and Oded Stein
Author-email: sgsellan@cs.toronto.edu
License: MIT
License-File: LICENSE.GPL
License-File: LICENSE.MIT
Requires-Dist: numpy<2.3,>=1.22.4
Requires-Dist: scipy<=1.15,>=1.7
Requires-Dist: scikit-image
Requires-Dist: scs
Dynamic: author
Dynamic: author-email
Dynamic: description
Dynamic: description-content-type
Dynamic: home-page
Dynamic: license
Dynamic: license-file
Dynamic: requires-dist
Dynamic: summary
